depth_anything_3/__init__.py
depth_anything_3/api.py
depth_anything_3/cache.py
depth_anything_3/cfg.py
depth_anything_3/cli.py
depth_anything_3/registry.py
depth_anything_3/specs.py
depth_anything_3/app/css_and_html.py
depth_anything_3/app/gradio_app.py
depth_anything_3/app/modules/__init__.py
depth_anything_3/app/modules/event_handlers.py
depth_anything_3/app/modules/file_handlers.py
depth_anything_3/app/modules/model_inference.py
depth_anything_3/app/modules/ui_components.py
depth_anything_3/app/modules/utils.py
depth_anything_3/app/modules/visualization.py
depth_anything_3/configs/da3-base.yaml
depth_anything_3/configs/da3-giant.yaml
depth_anything_3/configs/da3-large.yaml
depth_anything_3/configs/da3-small.yaml
depth_anything_3/configs/da3metric-large.yaml
depth_anything_3/configs/da3mono-large.yaml
depth_anything_3/configs/da3nested-giant-large.yaml
depth_anything_3/model/__init__.py
depth_anything_3/model/cam_dec.py
depth_anything_3/model/cam_enc.py
depth_anything_3/model/da3.py
depth_anything_3/model/dpt.py
depth_anything_3/model/dualdpt.py
depth_anything_3/model/gs_adapter.py
depth_anything_3/model/gsdpt.py
depth_anything_3/model/reference_view_selector.py
depth_anything_3/model/dinov2/dinov2.py
depth_anything_3/model/dinov2/vision_transformer.py
depth_anything_3/model/dinov2/layers/__init__.py
depth_anything_3/model/dinov2/layers/attention.py
depth_anything_3/model/dinov2/layers/block.py
depth_anything_3/model/dinov2/layers/drop_path.py
depth_anything_3/model/dinov2/layers/layer_scale.py
depth_anything_3/model/dinov2/layers/mlp.py
depth_anything_3/model/dinov2/layers/patch_embed.py
depth_anything_3/model/dinov2/layers/rope.py
depth_anything_3/model/dinov2/layers/swiglu_ffn.py
depth_anything_3/model/utils/attention.py
depth_anything_3/model/utils/block.py
depth_anything_3/model/utils/gs_renderer.py
depth_anything_3/model/utils/head_utils.py
depth_anything_3/model/utils/transform.py
depth_anything_3/services/__init__.py
depth_anything_3/services/backend.py
awesome_depth_anything_3-1.0.0.dist-info/METADATA
awesome_depth_anything_3-1.0.0.dist-info/WHEEL
awesome_depth_anything_3-1.0.0.dist-info/entry_points.txt
awesome_depth_anything_3-1.0.0.dist-info/licenses/LICENSE
awesome_depth_anything_3-1.0.0.dist-info/RECORD
