Metadata-Version: 2.4
Name: awesome-depth-anything-3
Version: 1.0.0
Summary: Optimized wrapper for Depth Anything 3 - Metric depth, point clouds, camera poses and novel views from any images
Project-URL: Homepage, https://github.com/Aedelon/awesome-depth-anything-3
Project-URL: Repository, https://github.com/Aedelon/awesome-depth-anything-3
Project-URL: Documentation, https://github.com/Aedelon/awesome-depth-anything-3#readme
Project-URL: Issues, https://github.com/Aedelon/awesome-depth-anything-3/issues
Project-URL: Changelog, https://github.com/Aedelon/awesome-depth-anything-3/blob/main/CHANGELOG.md
Project-URL: Upstream, https://github.com/ByteDance-Seed/Depth-Anything-3
Author-email: Delanoe Pirard <delanoe.pirard.pro@gmail.com>
License: Apache-2.0
License-File: LICENSE
Keywords: 3d-reconstruction,computer-vision,depth-estimation,monocular-depth,multi-view,point-cloud,pose-estimation,pytorch
Classifier: Development Status :: 4 - Beta
Classifier: Intended Audience :: Developers
Classifier: Intended Audience :: Science/Research
Classifier: License :: OSI Approved :: Apache Software License
Classifier: Programming Language :: Python :: 3.10
Classifier: Programming Language :: Python :: 3.11
Classifier: Programming Language :: Python :: 3.12
Classifier: Topic :: Scientific/Engineering :: Artificial Intelligence
Classifier: Topic :: Scientific/Engineering :: Image Processing
Requires-Python: <=3.13,>=3.10
Requires-Dist: e3nn
Requires-Dist: einops
Requires-Dist: evo
Requires-Dist: fastapi
Requires-Dist: huggingface-hub
Requires-Dist: imageio
Requires-Dist: kornia>=0.7.0
Requires-Dist: moviepy==1.0.3
Requires-Dist: numpy<2
Requires-Dist: omegaconf
Requires-Dist: open3d
Requires-Dist: opencv-python
Requires-Dist: pillow
Requires-Dist: pillow-heif
Requires-Dist: plyfile
Requires-Dist: pycolmap
Requires-Dist: requests
Requires-Dist: safetensors
Requires-Dist: torch>=2
Requires-Dist: torchvision
Requires-Dist: trimesh
Requires-Dist: typer>=0.12.0
Requires-Dist: uvicorn
Provides-Extra: all
Requires-Dist: gradio<6.0,>=5.50.0; extra == 'all'
Requires-Dist: gsplat>=1.0.0; (platform_system != 'Darwin') and extra == 'all'
Requires-Dist: huggingface-hub<2.0,>=0.33.5; extra == 'all'
Requires-Dist: pillow>=9.0; extra == 'all'
Requires-Dist: xformers; (platform_system != 'Darwin') and extra == 'all'
Provides-Extra: app
Requires-Dist: gradio<6.0,>=5.50.0; extra == 'app'
Requires-Dist: huggingface-hub<2.0,>=0.33.5; extra == 'app'
Requires-Dist: pillow>=9.0; extra == 'app'
Provides-Extra: cuda
Requires-Dist: gsplat>=1.0.0; (platform_system != 'Darwin') and extra == 'cuda'
Requires-Dist: xformers; (platform_system != 'Darwin') and extra == 'cuda'
Provides-Extra: dev
Requires-Dist: pre-commit; extra == 'dev'
Requires-Dist: pytest; extra == 'dev'
Requires-Dist: ruff; extra == 'dev'
Provides-Extra: gs
Requires-Dist: gsplat>=1.0.0; (platform_system != 'Darwin') and extra == 'gs'
Provides-Extra: xformers
Requires-Dist: xformers; (platform_system != 'Darwin') and extra == 'xformers'
